simplemseed_obspy_plugin/__init__.py
simplemseed_obspy_plugin/core.py
simplemseed_obspy_plugin/tests/__init__.py
simplemseed_obspy_plugin/tests/test_mseed3_read_write.py
simplemseed_obspy_plugin/tests/data/bird_jsc.ms3
simplemseed_obspy_plugin/tests/data/bird_jsc_recomp_int32.ms3
simplemseed_obspy_plugin/tests/data/casee_two.ms3
simplemseed_obspy_plugin/tests/data/reference-data/README.md
simplemseed_obspy_plugin/tests/data/reference-data/reference-detectiononly.json
simplemseed_obspy_plugin/tests/data/reference-data/reference-detectiononly.mseed3
simplemseed_obspy_plugin/tests/data/reference-data/reference-sinusoid-FDSN-All.json
simplemseed_obspy_plugin/tests/data/reference-data/reference-sinusoid-FDSN-All.mseed3
simplemseed_obspy_plugin/tests/data/reference-data/reference-sinusoid-FDSN-Other.json
simplemseed_obspy_plugin/tests/data/reference-data/reference-sinusoid-FDSN-Other.mseed3
simplemseed_obspy_plugin/tests/data/reference-data/reference-sinusoid-TQ-TC-ED.json
simplemseed_obspy_plugin/tests/data/reference-data/reference-sinusoid-TQ-TC-ED.mseed3
simplemseed_obspy_plugin/tests/data/reference-data/reference-sinusoid-float32.json
simplemseed_obspy_plugin/tests/data/reference-data/reference-sinusoid-float32.mseed3
simplemseed_obspy_plugin/tests/data/reference-data/reference-sinusoid-float64.json
simplemseed_obspy_plugin/tests/data/reference-data/reference-sinusoid-float64.mseed3
simplemseed_obspy_plugin/tests/data/reference-data/reference-sinusoid-int16.json
simplemseed_obspy_plugin/tests/data/reference-data/reference-sinusoid-int16.mseed3
simplemseed_obspy_plugin/tests/data/reference-data/reference-sinusoid-int32.json
simplemseed_obspy_plugin/tests/data/reference-data/reference-sinusoid-int32.mseed3
simplemseed_obspy_plugin/tests/data/reference-data/reference-sinusoid-steim1.json
simplemseed_obspy_plugin/tests/data/reference-data/reference-sinusoid-steim1.mseed3
simplemseed_obspy_plugin/tests/data/reference-data/reference-sinusoid-steim2.json
simplemseed_obspy_plugin-0.4.4.dist-info/METADATA
simplemseed_obspy_plugin-0.4.4.dist-info/WHEEL
simplemseed_obspy_plugin-0.4.4.dist-info/entry_points.txt
simplemseed_obspy_plugin-0.4.4.dist-info/licenses/LICENSE
simplemseed_obspy_plugin-0.4.4.dist-info/RECORD
