Metadata-Version: 2.4
Name: simplemseed-obspy-plugin
Version: 0.4.4
Summary: obspy plugin for miniseed3 in pure python
Project-URL: Homepage, https://github.com/crotwell/simplemseed_obspy_plugin
Project-URL: Documentation, https://github.com/crotwell/simplemseed_obspy_plugin
Project-URL: Repository, https://github.com/crotwell/simplemseed_obspy_plugin
Project-URL: Issues, https://github.com/crotwell/simplemseed_obspy_plugin/issues
Author-email: Philip Crotwell <crotwell@seis.sc.edu>
License-File: LICENSE
Keywords: fdsn,miniseed3,obspy,seed,sourceid,steim1,steim2
Classifier: License :: OSI Approved :: GNU Lesser General Public License v2 or later (LGPLv2+)
Classifier: Operating System :: OS Independent
Classifier: Programming Language :: Python :: 3
Requires-Python: >=3.9
Requires-Dist: crc32c
Requires-Dist: importlib-metadata; python_version < '3.10'
Requires-Dist: jsonpointer
Requires-Dist: numpy
Requires-Dist: obspy
Requires-Dist: simplemseed>=0.4.4
